{
  "id": "petroleum",
  "description": "EIA petroleum gas survey data",
  "frequency": [
    {
      "id": "monthly",
      "description": "One data point for each month.",
      "query": "M",
      "format": "YYYY-MM"
    },
    {
      "id": "annual",
      "description": "One data point for each calendar year.",
      "query": "A",
      "format": "YYYY"
    }
  ],
  "facets": [
    {
      "id": "duoarea",
      "description": "DuoArea"
    },
    {
      "id": "product",
      "description": "Product"
    },
    {
      "id": "process",
      "description": "Process"
    },
    {
      "id": "series",
      "description": "Series"
    }
  ],
  "data": {
    "value": []
  },
  "startPeriod": "1993-10",
  "endPeriod": "2023-12",
  "defaultDateFormat": "YYYY-MM",
  "defaultFrequency": "monthly"
}
